{"grandtotal_skipped_frames": 51956, "total_ingame_skipped_frames": 32966, "match_data": {"1744283": {"skipped_frames": 0}, "1745658": {"skipped_frames": 654}, "1746101": {"skipped_frames": 1279}, "1746437": {"skipped_frames": 2576}, "1746775": {"skipped_frames": 3080}, "1746997": {"skipped_frames": 5521}, "1747509": {"skipped_frames": 5872}, "1747776": {"skipped_frames": 6226}, "1748164": {"skipped_frames": 6226}, "1748783": {"skipped_frames": 6598}, "1751541": {"skipped_frames": 653}, "1752038": {"skipped_frames": 25677}, "1752477": {"skipped_frames": 26026}, "1752700": {"skipped_frames": 26368}, "1753059": {"skipped_frames": 26368}}}